buenavista/__init__.py
buenavista/bv_dialects.py
buenavista/core.py
buenavista/postgres.py
buenavista/rewrite.py
buenavista/backends/__init__.py
buenavista/backends/duckdb.py
buenavista/backends/postgres.py
buenavista/examples/duckdb_http.py
buenavista/examples/duckdb_postgres.py
buenavista/examples/postgres_proxy.py
buenavista/http/__init__.py
buenavista/http/context.py
buenavista/http/main.py
buenavista/http/schemas.py
buenavista/http/type_mapping.py
buenavista-0.5.0.dist-info/LICENSE
buenavista-0.5.0.dist-info/METADATA
buenavista-0.5.0.dist-info/WHEEL
buenavista-0.5.0.dist-info/top_level.txt
buenavista-0.5.0.dist-info/RECORD
