Metadata-Version: 2.1
Name: buenavista
Version: 0.5.0
Summary: Programmable Presto and Postgres Proxies
Home-page: https://github.com/jwills/buenavista
Author: Josh Wills
Author-email: joshwills+bv@gmail.com
License: Apache
License-File: LICENSE
Requires-Dist: fastapi<1.0.0,>=0.109.0
Requires-Dist: pydantic<3,>=2
Requires-Dist: sqlglot
Provides-Extra: duckdb
Requires-Dist: duckdb; extra == "duckdb"
Requires-Dist: pyarrow; extra == "duckdb"
Provides-Extra: postgres
Requires-Dist: psycopg; extra == "postgres"
Requires-Dist: psycopg-pool; extra == "postgres"
